aiohwenergy/__init__.py
aiohwenergy/data.py
aiohwenergy/device.py
aiohwenergy/errors.py
aiohwenergy/hwenergy.py
aiohwenergy/state.py
aiohwenergy-0.8.0.dist-info/LICENSE
aiohwenergy-0.8.0.dist-info/METADATA
aiohwenergy-0.8.0.dist-info/WHEEL
aiohwenergy-0.8.0.dist-info/top_level.txt
aiohwenergy-0.8.0.dist-info/zip-safe
aiohwenergy-0.8.0.dist-info/RECORD
