Metadata-Version: 2.1
Name: aiohwenergy
Version: 0.8.0
Summary: Python module to talk to HomeWizard Energy Devices.
Home-page: https://github.com/DCSBL/aiohwenergy
Author: DCSBL
Author-email: github@ducosebel.nl
License: Apache License 2.0
Platform: UNKNOWN
Classifier: Development Status :: 4 - Beta
Classifier: Intended Audience :: Developers
Classifier: Operating System :: OS Independent
Classifier: Programming Language :: Python :: 3 :: Only
Classifier: Topic :: Software Development :: Libraries :: Python Modules
License-File: LICENSE
Requires-Dist: aiohttp
